README.md
setup.py
traj_dist/__init__.py
traj_dist/benchmark.py
traj_dist/build_benchmark_data.py
traj_dist/distance.py
traj_dist/example.py
traj_dist/cydist/__init__.py
traj_dist/cydist/basic_euclidean.pyx
traj_dist/cydist/basic_geographical.pyx
traj_dist/cydist/discret_frechet.pyx
traj_dist/cydist/dtw.pyx
traj_dist/cydist/edr.pyx
traj_dist/cydist/erp.pyx
traj_dist/cydist/frechet.pyx
traj_dist/cydist/hausdorff.pyx
traj_dist/cydist/lcss.pyx
traj_dist/cydist/segment_distance.pyx
traj_dist/cydist/sowd.pyx
traj_dist/cydist/sspd.pyx
traj_dist/pydist/__init__.py
traj_dist/pydist/basic_euclidean.py
traj_dist/pydist/basic_spherical.py
traj_dist/pydist/discret_frechet.py
traj_dist/pydist/dtw.py
traj_dist/pydist/edr.py
traj_dist/pydist/erp.py
traj_dist/pydist/frechet.py
traj_dist/pydist/hausdorff.py
traj_dist/pydist/lcss.py
traj_dist/pydist/linecell.py
traj_dist/pydist/segment_distance.py
traj_dist/pydist/sowd.py
traj_dist/pydist/sspd.py
trajectory_distance.egg-info/PKG-INFO
trajectory_distance.egg-info/SOURCES.txt
trajectory_distance.egg-info/dependency_links.txt
trajectory_distance.egg-info/requires.txt
trajectory_distance.egg-info/top_level.txt