Metadata-Version: 1.0
Name: trajectory_distance
Version: 1.0
Summary: Distance to compare 2D-trajectories in Cython
Home-page: UNKNOWN
Author: Brendan Guillouet
Author-email: brendan.guillouet@gmail.com
License: UNKNOWN
Platform: UNKNOWN
